get_tmp_creds/__init__.py
get_tmp_creds/main.py
get_tmp_creds-1.0.dist-info/LICENSE
get_tmp_creds-1.0.dist-info/METADATA
get_tmp_creds-1.0.dist-info/WHEEL
get_tmp_creds-1.0.dist-info/entry_points.txt
get_tmp_creds-1.0.dist-info/top_level.txt
get_tmp_creds-1.0.dist-info/RECORD
