Metadata-Version: 2.1
Name: get-tmp-creds
Version: 1.0
Summary: A CLI tool for managing AWS SSO temporary credentials.
Home-page: https://github.com/aderbique/get-tmp-creds
Author: Austin Derbique
Author-email: austin@derbique.org
License: MIT
Platform: UNKNOWN
License-File: LICENSE
Requires-Dist: click
Requires-Dist: boto3
